ocr2text/__init__.py
ocr2text/main.py
ocr2text-0.1.0.dist-info/METADATA
ocr2text-0.1.0.dist-info/WHEEL
ocr2text-0.1.0.dist-info/top_level.txt
ocr2text-0.1.0.dist-info/RECORD
