Metadata-Version: 2.4
Name: ocr2text
Version: 0.1.0
Summary: Convert scanned PDFs to text file using OCR
Home-page: https://github.com/krishna525/free-ocr-pdf-maker
Author: Krishna
Author-email: krishna857191@gmail.com
Classifier: Programming Language :: Python :: 3
Classifier: License :: OSI Approved :: MIT License
Classifier: Operating System :: OS Independent
Requires-Python: >=3.7
Requires-Dist: requests
Requires-Dist: websocket-client
Dynamic: author
Dynamic: author-email
Dynamic: classifier
Dynamic: description
Dynamic: description-content-type
Dynamic: home-page
Dynamic: requires-dist
Dynamic: requires-python
Dynamic: summary
